[
  {
    "FirstName": "Carver",
    "LastName": "Wilkerson",
    "society": ", C.B.",
    "company_": "DANCITY",
    "company": "DANCITY, C.B.",
    "NIF": "B16610361",
    "JobTitle": "Jefe Dpto. Técnico",
    "Adress": "355 Beverly Road,",
    "City": " Orin",
    "State_Province": "American Samoa",
    "ZIP_PostalCode": 11328,
    "Country": "Samoa",
    "email": "carver.wilkerson@dancity.net",
    "phone": "+1 (954) 565-2647",
    "Observations": "",
    "isDeleted": false,
    "isActive": false,
    "registered": "2018-08-22",
    "TenantId": 1
  },
  {
    "FirstName": "Gwen",
    "LastName": "Mcgee",
    "society": ", C.B.",
    "company_": "PEARLESSA",
    "company": "PEARLESSA, C.B.",
    "NIF": "B04632917",
    "JobTitle": "Jefe Dpto. Técnico",
    "Adress": "368 Ash Street,",
    "City": " Darrtown",
    "State_Province": "North Carolina",
    "ZIP_PostalCode": 11174,
    "Country": "Slovak Republic",
    "email": "gwen.mcgee@pearlessa.us",
    "phone": "+1 (808) 506-2675",
    "Observations": "",
    "isDeleted": false,
    "isActive": true,
    "registered": "2014-01-11",
    "TenantId": 1
  },
  {
    "FirstName": "Alfreda",
    "LastName": "Bridges",
    "society": ", S.C.",
    "company_": "GENMY",
    "company": "GENMY, S.C.",
    "NIF": "B66001615",
    "JobTitle": "Gerente",
    "Adress": "927 Albee Square,",
    "City": " Avalon",
    "State_Province": "Maryland",
    "ZIP_PostalCode": 11828,
    "Country": "Brunei Darussalam",
    "email": "alfreda.bridges@genmy.com",
    "phone": "+1 (942) 528-2089",
    "Observations": "",
    "isDeleted": false,
    "isActive": false,
    "registered": "2017-04-30",
    "TenantId": 1
  },
  {
    "FirstName": "Mcpherson",
    "LastName": "Larson",
    "society": ", C.B.",
    "company_": "SHEPARD",
    "company": "SHEPARD, C.B.",
    "NIF": "B72398015",
    "JobTitle": "Jefe Dpto. Técnico",
    "Adress": "288 Bartlett Street,",
    "City": " Nicut",
    "State_Province": "Michigan",
    "ZIP_PostalCode": 11147,
    "Country": "Aruba",
    "email": "mcpherson.larson@shepard.name",
    "phone": "+1 (971) 460-3399",
    "Observations": "",
    "isDeleted": false,
    "isActive": true,
    "registered": "2016-09-02",
    "TenantId": 1
  },
  {
    "FirstName": "Celeste",
    "LastName": "Greer",
    "society": ", S.C.",
    "company_": "SECURIA",
    "company": "SECURIA, S.C.",
    "NIF": "B58922395",
    "JobTitle": "Director Técnico",
    "Adress": "843 Winthrop Street,",
    "City": " Tilden",
    "State_Province": "South Dakota",
    "ZIP_PostalCode": 11932,
    "Country": "Mauritania",
    "email": "celeste.greer@securia.biz",
    "phone": "+1 (933) 408-3696",
    "Observations": "",
    "isDeleted": false,
    "isActive": true,
    "registered": "2016-08-24",
    "TenantId": 1
  },
  {
    "FirstName": "Allen",
    "LastName": "Morse",
    "society": ", S.A.",
    "company_": "ZOLAR",
    "company": "ZOLAR, S.A.",
    "NIF": "B81394774",
    "JobTitle": "Director Técnico",
    "Adress": "968 Kingsway Place,",
    "City": " Dragoon",
    "State_Province": "Kansas",
    "ZIP_PostalCode": 11085,
    "Country": "Bosnia and Herzegovina",
    "email": "allen.morse@zolar.info",
    "phone": "+1 (947) 481-3042",
    "Observations": "",
    "isDeleted": false,
    "isActive": false,
    "registered": "2015-09-17",
    "TenantId": 1
  },
  {
    "FirstName": "Patrice",
    "LastName": "Wilkins",
    "society": ", S.C.",
    "company_": "MIRACULA",
    "company": "MIRACULA, S.C.",
    "NIF": "B50438065",
    "JobTitle": "Ingeniero Jefe",
    "Adress": "292 Delmonico Place,",
    "City": " Reinerton",
    "State_Province": "Illinois",
    "ZIP_PostalCode": 11539,
    "Country": "Reunion",
    "email": "patrice.wilkins@miracula.org",
    "phone": "+1 (847) 513-3677",
    "Observations": "",
    "isDeleted": false,
    "isActive": true,
    "registered": "2014-09-21",
    "TenantId": 1
  },
  {
    "FirstName": "Heidi",
    "LastName": "Bennett",
    "society": ", S.A.",
    "company_": "NEUROCELL",
    "company": "NEUROCELL, S.A.",
    "NIF": "B51599653",
    "JobTitle": "Jefe Dpto. Técnico",
    "Adress": "569 Garden Place,",
    "City": " Washington",
    "State_Province": "Palau",
    "ZIP_PostalCode": 11495,
    "Country": "Belarus",
    "email": "heidi.bennett@neurocell.biz",
    "phone": "+1 (981) 504-2383",
    "Observations": "",
    "isDeleted": false,
    "isActive": true,
    "registered": "2015-10-16",
    "TenantId": 1
  },
  {
    "FirstName": "Ellison",
    "LastName": "Bender",
    "society": ", S.L.",
    "company_": "TINGLES",
    "company": "TINGLES, S.L.",
    "NIF": "B31200422",
    "JobTitle": "Jefe Dpto. Técnico",
    "Adress": "862 Madoc Avenue,",
    "City": " Chesterfield",
    "State_Province": "Idaho",
    "ZIP_PostalCode": 11256,
    "Country": "Costa Rica",
    "email": "ellison.bender@tingles.co.uk",
    "phone": "+1 (999) 410-2387",
    "Observations": "",
    "isDeleted": false,
    "isActive": true,
    "registered": "2017-08-28",
    "TenantId": 1
  },
  {
    "FirstName": "Merrill",
    "LastName": "Haney",
    "society": ", C.B.",
    "company_": "GINKOGENE",
    "company": "GINKOGENE, C.B.",
    "NIF": "B20763571",
    "JobTitle": "Gerente",
    "Adress": "548 Boardwalk ,",
    "City": " Leland",
    "State_Province": "Delaware",
    "ZIP_PostalCode": 11951,
    "Country": "Iran",
    "email": "merrill.haney@ginkogene.tv",
    "phone": "+1 (905) 422-2948",
    "Observations": "",
    "isDeleted": false,
    "isActive": false,
    "registered": "2015-07-18",
    "TenantId": 1
  },
  {
    "FirstName": "Ronda",
    "LastName": "Cannon",
    "society": ", S.COOP.",
    "company_": "BIOLIVE",
    "company": "BIOLIVE, S.COOP.",
    "NIF": "B94058128",
    "JobTitle": "Ingeniero Jefe",
    "Adress": "459 Varet Street,",
    "City": " Coultervillle",
    "State_Province": "Kentucky",
    "ZIP_PostalCode": 11613,
    "Country": "French Southern Territories",
    "email": "ronda.cannon@biolive.ca",
    "phone": "+1 (953) 501-3822",
    "Observations": "",
    "isDeleted": false,
    "isActive": false,
    "registered": "2014-04-27",
    "TenantId": 1
  }
]